README.md
setup.py
logrun/__init__.py
logrun/internals.py
logrun.egg-info/PKG-INFO
logrun.egg-info/SOURCES.txt
logrun.egg-info/dependency_links.txt
logrun.egg-info/requires.txt
logrun.egg-info/top_level.txt
logrun/utils/__init__.py
logrun/utils/data.py
logrun/utils/general.py
logrun/utils/media.py
logrun/utils/ml.py