Metadata-Version: 2.1
Name: logrun
Version: 0.1.2
Summary: A convenient experiment logging package for Python
Home-page: https://github.com/dccsillag/logrun
Author: Daniel Csillag
Author-email: dccsillag@gmail.com
License: MIT
Platform: UNKNOWN
Provides-Extra: utils-media
Provides-Extra: utils-data
Provides-Extra: utils-ml-cpu
Provides-Extra: utils-ml-gpu
